[
  {
    "title": "Adjustable Leather Barefoot Sandals - black Flat Sandals for",
    "price": "$86",
    "image_url": "https://cdn.faire.com/fastly/6208c1fc44c2deac96ae799ea0c7b01011f8f64519352dee6b7ab3736ec96382.jpeg",
    "product_url": "https://www.faire.com",
    "brand": "Moroccan Footwear",
    "primary_color": "dark_gray",
    "primary_color_hex": "#111111"
  },
  {
    "title": "Adjustable Leather Barefoot Sandals - Multicolor Flat Sandal",
    "price": "$73",
    "image_url": "https://cdn.faire.com/fastly/8ed0f055aff2aaed0da00a153a4afe2844de5a546ffe08a66df5e71ba0cb5bb3.jpeg",
    "product_url": "https://www.faire.com",
    "brand": "Moroccan Footwear",
    "primary_color": "dark_gray",
    "primary_color_hex": "#111111"
  },
  {
    "title": "Adjustable Leather Barefoot Sandals - white Flat Sandals for",
    "price": "$97",
    "image_url": "https://cdn.faire.com/fastly/d497c7729c51775dbccd28ce2cb37ffe8ef6b173e6ea60f968966b959a957c52.jpeg",
    "product_url": "https://www.faire.com",
    "brand": "Moroccan Footwear",
    "primary_color": "dark_gray",
    "primary_color_hex": "#111111"
  },
  {
    "title": "Adjustable Leather Barefoot Sandals - zebra Flat Sandals for",
    "price": "$97",
    "image_url": "https://cdn.faire.com/fastly/bc3660424af4139fd0c07075e6f4317d8f54f529ea30769320dd63e97bd0ce2b.jpeg",
    "product_url": "https://www.faire.com",
    "brand": "Moroccan Footwear",
    "primary_color": "dark_gray",
    "primary_color_hex": "#111111"
  },
  {
    "title": "Artisan Embroidered Platform Babouche Mules",
    "price": "$45",
    "image_url": "https://cdn.faire.com/fastly/bb023ca480c1edebd1db76a1b2a0d3fdabf5179be0f531a85420ae6cee2c50b1.jpeg",
    "product_url": "https://www.faire.com",
    "brand": "Moroccan Footwear",
    "primary_color": "beige",
    "primary_color_hex": "#e8d8c8"
  },
  {
    "title": "Artisan Leather Moroccan Babouche Slippers - Espresso",
    "price": "$45",
    "image_url": "https://cdn.faire.com/fastly/5cc54d2fb05aa11005c84ea7ed5f3c6cdd09c718d1cffa343bc27f536af6fd5a.png",
    "product_url": "https://www.faire.com",
    "brand": "Moroccan Footwear",
    "primary_color": "beige",
    "primary_color_hex": "#e8d8c8"
  },
  {
    "title": "Artisan Tan Leather Studded H-Strap Sandals",
    "price": "$45",
    "image_url": "https://cdn.faire.com/fastly/312bdf824f33594aaa9ca620d9953b006dcaad6d92532234f6cc63360abf3a32.png",
    "product_url": "https://www.faire.com",
    "brand": "Moroccan Footwear",
    "primary_color": "beige",
    "primary_color_hex": "#e8d8c8"
  },
  {
    "title": "Artisan Woven Leather Sandals Handmade in Marrakesh",
    "price": "$45",
    "image_url": "https://cdn.faire.com/fastly/a3ec6d1a440adb225649ac9a3f2413388ff8b0548178c8b1dacbd5c95cc2afc2.png",
    "product_url": "https://www.faire.com",
    "brand": "Moroccan Footwear",
    "primary_color": "beige",
    "primary_color_hex": "#e8d8c8"
  },
  {
    "title": "Artisanal Embroidered Platform Slides with Pom-Poms",
    "price": "$45",
    "image_url": "https://cdn.faire.com/fastly/d3ee9333ca770020b1038197cbff8d09ee5ef724719ba302a1d1da1cc6796e42.jpeg",
    "product_url": "https://www.faire.com",
    "brand": "Moroccan Footwear",
    "primary_color": "beige",
    "primary_color_hex": "#e8d8c8"
  },
  {
    "title": "Babouche marocaine noire en cuir - Chaussons classiques fait",
    "price": "$89",
    "image_url": "https://cdn.faire.com/fastly/d57fbd91f62fd7ac69e42325d21d5b484d0a077d559fc109c446376e9b6f41e8.jpeg",
    "product_url": "https://www.faire.com",
    "brand": "Moroccan Footwear",
    "primary_color": "brown",
    "primary_color_hex": "#8b5a2b"
  },
  {
    "title": "Black, Braided, Leather, Slide Sandals, Women, Handmade, One",
    "price": "$87",
    "image_url": "https://cdn.faire.com/fastly/21079949b788f5c3deaac852a10908f34d46d14e660d4b8635240f850017b6ff.jpeg",
    "product_url": "https://www.faire.com",
    "brand": "Moroccan Footwear",
    "primary_color": "brown",
    "primary_color_hex": "#8b5a2b"
  },
  {
    "title": "Blue Moroccan Leather Babouche – Unisex Handmade Traditional",
    "price": "$87",
    "image_url": "https://cdn.faire.com/fastly/861066438fa71ef0457414406001e1a5dad210f0920cd53be9058a49b0b13d4c.jpeg",
    "product_url": "https://www.faire.com",
    "brand": "Moroccan Footwear",
    "primary_color": "brown",
    "primary_color_hex": "#8b5a2b"
  },
  {
    "title": "Bright Yellow Moroccan Leather Babouche – Handmade Tradition",
    "price": "$89",
    "image_url": "https://cdn.faire.com/fastly/eb234952852ed37f79f530ec5f9788f4afb0837689a6c7e11a6540075b90b16c.jpeg",
    "product_url": "https://www.faire.com",
    "brand": "Moroccan Footwear",
    "primary_color": "brown",
    "primary_color_hex": "#8b5a2b"
  },
  {
    "title": "Brown Leather Barefoot Sandals: Adjustable Flat Sandals for",
    "price": "$86",
    "image_url": "https://cdn.faire.com/fastly/67170f8d64f0b85a6e1a017a13df09ec473eb6235f3c7d953d811e25386e3b23.jpeg",
    "product_url": "https://www.faire.com",
    "brand": "Moroccan Footwear",
    "primary_color": "dark_gray",
    "primary_color_hex": "#111111"
  },
  {
    "title": "Brown Leather Barefoot Sandals: Adjustable Women's Flat Sand",
    "price": "$82",
    "image_url": "https://cdn.faire.com/fastly/c8750444538214709db4073d5a2b501adcfb98e2d690747920702066b4bb7bd8.jpeg",
    "product_url": "https://www.faire.com",
    "brand": "Moroccan Footwear",
    "primary_color": "dark_gray",
    "primary_color_hex": "#111111"
  },
  {
    "title": "Classic Black Handmade Leather Sandals for Men – Moroccan Cr",
    "price": "$86",
    "image_url": "https://cdn.faire.com/fastly/e309ab5fedb0b932530842a825f6ba79883b7f76f965f8875768d35a2bd51a0b.jpeg",
    "product_url": "https://www.faire.com",
    "brand": "Moroccan Footwear",
    "primary_color": "brown",
    "primary_color_hex": "#8b5a2b"
  },
  {
    "title": "CROSS STRAPS SLIDES.men leather sandals Moroccan",
    "price": "$73",
    "image_url": "https://cdn.faire.com/fastly/6db16890441ab23519e4bf2fb22681955ef36b227aa4f37ccf19ea91bf3e563b.jpeg",
    "product_url": "https://www.faire.com",
    "brand": "Moroccan Footwear",
    "primary_color": "beige",
    "primary_color_hex": "#e8d8c8"
  },
  {
    "title": "Dark Blue Suede Leather Moroccan Babouche Slippers, Handmade",
    "price": "$75",
    "image_url": "https://cdn.faire.com/fastly/4c3acfa4649b13235b32c86b19a9650cb77c9915ce45908c9d828f1295b6c230.jpeg",
    "product_url": "https://www.faire.com",
    "brand": "Moroccan Footwear",
    "primary_color": "brown",
    "primary_color_hex": "#8b5a2b"
  },
  {
    "title": "Genuine leather sandal, Genuine leather thongs,100% handmade",
    "price": "$45",
    "image_url": "https://cdn.faire.com/fastly/6f9fbaeb506878b4b9aa3fd4f48032fa37c91c748a8a6d62065a8a81376f3650.jpeg",
    "product_url": "https://www.faire.com",
    "brand": "Moroccan Footwear",
    "primary_color": "beige",
    "primary_color_hex": "#e8d8c8"
  },
  {
    "title": "Gold Leather Pointed-Toe Mules with Tassels.",
    "price": "$45",
    "image_url": "https://cdn.faire.com/fastly/4dd2451f39ff8b94c5becc97fb77a3dd2b3ffbc1a85ef0d1ad2e4c593f45329f.jpeg",
    "product_url": "https://www.faire.com",
    "brand": "Moroccan Footwear",
    "primary_color": "beige",
    "primary_color_hex": "#e8d8c8"
  },
  {
    "title": "Green Moroccan House Slippers, Handmade Leather Indoor Shoes",
    "price": "$75",
    "image_url": "https://cdn.faire.com/fastly/bb7c316c49e554e5def37b0dec6adc90e0ffeed80e965039f9b4d4c7188d4bb9.jpeg",
    "product_url": "https://www.faire.com",
    "brand": "Moroccan Footwear",
    "primary_color": "brown",
    "primary_color_hex": "#8b5a2b"
  },
  {
    "title": "Handcrafted Artisan Leather Toe-Loop Sandals – Premium Tan",
    "price": "$45",
    "image_url": "https://cdn.faire.com/fastly/41c4f9284b6214a6b75eec1db8bc9d248c1b06c2cd0bddf591f21ce57f4d8ea8.png",
    "product_url": "https://www.faire.com",
    "brand": "Moroccan Footwear",
    "primary_color": "beige",
    "primary_color_hex": "#e8d8c8"
  },
  {
    "title": "Handcrafted Moroccan Leather Slide Sandals",
    "price": "$45",
    "image_url": "https://cdn.faire.com/fastly/05de9937d050d9616e9e12433e8a08993a7fb745a71b933337abfa9345a68622.png",
    "product_url": "https://www.faire.com",
    "brand": "Moroccan Footwear",
    "primary_color": "beige",
    "primary_color_hex": "#e8d8c8"
  },
  {
    "title": "Handcrafted Moroccan Leather Slide Sandals Blue Strap",
    "price": "$45",
    "image_url": "https://cdn.faire.com/fastly/d4af406da69a8201cf25364a0793cf7337136cc93f1bc921a563c21f9e22a19f.png",
    "product_url": "https://www.faire.com",
    "brand": "Moroccan Footwear",
    "primary_color": "beige",
    "primary_color_hex": "#e8d8c8"
  },
  {
    "title": "Handmade animal print zebrz Leather Cross Sandals: Moroccan",
    "price": "$106",
    "image_url": "https://cdn.faire.com/fastly/658057415ed6aaad9bb699f9aea48c520d8fbde26a29445b163b2f4a546cf128.jpeg",
    "product_url": "https://www.faire.com",
    "brand": "Moroccan Footwear",
    "primary_color": "beige",
    "primary_color_hex": "#e8d8c8"
  },
  {
    "title": "Handmade Artisan Brown Leather Studded H-Strap Slides",
    "price": "$45",
    "image_url": "https://cdn.faire.com/fastly/ca2da0e425f63307832a7170010a51afaaf8d6dd40a64a8fac8e2457675c5f53.jpeg",
    "product_url": "https://www.faire.com",
    "brand": "Moroccan Footwear",
    "primary_color": "beige",
    "primary_color_hex": "#e8d8c8"
  },
  {
    "title": "Handmade Artisan Multi-Color Leather Sandals",
    "price": "$45",
    "image_url": "https://cdn.faire.com/fastly/5e421d04a7c6bae6d7d7e42a9a073f525d429d0eabcfb48b370c0daca4e5aae4.png",
    "product_url": "https://www.faire.com",
    "brand": "Moroccan Footwear",
    "primary_color": "beige",
    "primary_color_hex": "#e8d8c8"
  },
  {
    "title": "Handmade black Leather Cross-Strap Sandals: Comfortable Moro",
    "price": "$86",
    "image_url": "https://cdn.faire.com/fastly/8be7e84c758f80d3c49f4e36244601a4b4b144605990239b1b734521875e162e.jpeg",
    "product_url": "https://www.faire.com",
    "brand": "Moroccan Footwear",
    "primary_color": "dark_gray",
    "primary_color_hex": "#111111"
  },
  {
    "title": "Handmade Black Leather Flip Flops: Moroccan Boho Sandals",
    "price": "$73",
    "image_url": "https://cdn.faire.com/fastly/d7968bc2b0b06bd999527d500d9a19fdb4bb5fb9be4a42dc12374016e1c07504.jpeg",
    "product_url": "https://www.faire.com",
    "brand": "Moroccan Footwear",
    "primary_color": "brown",
    "primary_color_hex": "#8b5a2b"
  },
  {
    "title": "Handmade Black Leather Gladiator Sandals: Moroccan Summer Sh",
    "price": "$87",
    "image_url": "https://cdn.faire.com/fastly/d6f1ca0204170ff69acaa59601e102eecc0efb3f04bf6e989afa3f458b622f1d.jpeg",
    "product_url": "https://www.faire.com",
    "brand": "Moroccan Footwear",
    "primary_color": "brown",
    "primary_color_hex": "#8b5a2b"
  },
  {
    "title": "Handmade Black Leather Moroccan Sandals, Minimalist Summer S",
    "price": "$88",
    "image_url": "https://cdn.faire.com/fastly/0ffa356afc5ae5fe265c380545b44c2d841fc555b1ccf087af89482805fc460f.jpeg",
    "product_url": "https://www.faire.com",
    "brand": "Moroccan Footwear",
    "primary_color": "brown",
    "primary_color_hex": "#8b5a2b"
  },
  {
    "title": "Handmade Black Leather Sandals - Moroccan Slip-On Summer Sho",
    "price": "$133",
    "image_url": "https://cdn.faire.com/fastly/9d9318be8fc18f322351977643255fc92e8c64ca43bdfcbfe24417d7c71814fd.jpeg",
    "product_url": "https://www.faire.com",
    "brand": "Moroccan Footwear",
    "primary_color": "beige",
    "primary_color_hex": "#e8d8c8"
  },
  {
    "title": "Handmade Black Leather Sandals with Buckle – Unisex Moroccan",
    "price": "$97",
    "image_url": "https://cdn.faire.com/fastly/cd22340b246ec3e2f652490096923377da6f0ee34acd532f535bb2d2f9d5ab29.jpeg",
    "product_url": "https://www.faire.com",
    "brand": "Moroccan Footwear",
    "primary_color": "dark_gray",
    "primary_color_hex": "#111111"
  },
  {
    "title": "Handmade black Leather Sandals – Minimalist Cross-Strap Summ",
    "price": "$133",
    "image_url": "https://cdn.faire.com/fastly/ac10f3dc67d2d0d5dd523c102823ba26872ea16d79681341bd9a09adcd71451d.jpeg",
    "product_url": "https://www.faire.com",
    "brand": "Moroccan Footwear",
    "primary_color": "brown",
    "primary_color_hex": "#8b5a2b"
  },
  {
    "title": "Handmade Black Leather Toe-Loop Sandals - Artisanal Men's Sl",
    "price": "$45",
    "image_url": "https://cdn.faire.com/fastly/cec35483ef2d386acc4389f0c95b414d171482038d247b3abb710aa4c6d9577e.png",
    "product_url": "https://www.faire.com",
    "brand": "Moroccan Footwear",
    "primary_color": "beige",
    "primary_color_hex": "#e8d8c8"
  },
  {
    "title": "Handmade Braided Leather Belt - Moroccan Artisan Style",
    "price": "$78",
    "image_url": "https://cdn.faire.com/fastly/88ad4de051077a9ceed7dfa6bfc0d8566264277104fd53936e7e40bbb3ad7aa8.jpeg",
    "product_url": "https://www.faire.com",
    "brand": "Moroccan Footwear",
    "primary_color": "beige",
    "primary_color_hex": "#e8d8c8"
  },
  {
    "title": "Handmade Braided Leather Belt – Moroccan Artisan Accessory",
    "price": "$73",
    "image_url": "https://cdn.faire.com/fastly/d5ed8a5bd42fabdee860d09ba07d571dc61b5fecb29fc75e3087f649d705131a.jpeg",
    "product_url": "https://www.faire.com",
    "brand": "Moroccan Footwear",
    "primary_color": "beige",
    "primary_color_hex": "#e8d8c8"
  },
  {
    "title": "Handmade Braided Leather Sandals: Bohemian Chic Style",
    "price": "$76",
    "image_url": "https://cdn.faire.com/fastly/ef6b79e83dadef29a2a801645e8f4d6f1332b41011e538dfcfcffc3ed855d9d8.jpeg",
    "product_url": "https://www.faire.com",
    "brand": "Moroccan Footwear",
    "primary_color": "beige",
    "primary_color_hex": "#e8d8c8"
  },
  {
    "title": "Handmade Brown Boho Flats from Marrakech",
    "price": "$97",
    "image_url": "https://cdn.faire.com/fastly/77fafe239330b12f81d836e3ff251920285173d17c0f34aa40254adb6cffead0.jpeg",
    "product_url": "https://www.faire.com",
    "brand": "Moroccan Footwear",
    "primary_color": "beige",
    "primary_color_hex": "#e8d8c8"
  },
  {
    "title": "Handmade Brown Leather Cross Sandals: Moroccan Summer Shoes",
    "price": "$92",
    "image_url": "https://cdn.faire.com/fastly/ae429f730458038da7bf410f1e9e0afe8f35bda9c9b8166190ca38a13f63140e.jpeg",
    "product_url": "https://www.faire.com",
    "brand": "Moroccan Footwear",
    "primary_color": "beige",
    "primary_color_hex": "#e8d8c8"
  },
  {
    "title": "-Handmade Openwork Rope Basket-Moroccan Palm Leaf Bag",
    "price": "$45",
    "image_url": "https://cdn.faire.com/fastly/3c05984f8ac91acb6081fa6405ad106e8afdc803b6d0b385631e10e1a26c10e6.webp",
    "product_url": "https://www.faire.com",
    "brand": "Moroccan Bags",
    "primary_color": "brown",
    "primary_color_hex": "#8b5a2b"
  },
  {
    "title": "Artisan Boho Leather Crossbody: Handmade in Morocco",
    "price": "$45",
    "image_url": "https://cdn.faire.com/fastly/d9f6af24e649129d187c1f32a94f30f7ac9e98d34c402a871f470ae4d87f3d05.jpeg",
    "product_url": "https://www.faire.com",
    "brand": "Moroccan Bags",
    "primary_color": "beige",
    "primary_color_hex": "#e8d8c8"
  },
  {
    "title": "Artisan Coiled Raffia and Studded Leather Round Bag",
    "price": "$45",
    "image_url": "https://cdn.faire.com/fastly/cf7d07a29550dd068ff7b3d77d5b1fa907d7ec86377996d68a233e2be3d58853.png",
    "product_url": "https://www.faire.com",
    "brand": "Moroccan Bags",
    "primary_color": "beige",
    "primary_color_hex": "#e8d8c8"
  },
  {
    "title": "Artisan Embroidered Straw Bag: Handcrafted Elegance",
    "price": "$45",
    "image_url": "https://cdn.faire.com/fastly/42a593e285a1e3aa3b4f1e5b6bd1ee2537c6e140492877640f9b847baf3f5883.jpeg",
    "product_url": "https://www.faire.com",
    "brand": "Moroccan Bags",
    "primary_color": "beige",
    "primary_color_hex": "#e8d8c8"
  },
  {
    "title": "Artisan Evil Eye Woven Basket Tote",
    "price": "$45",
    "image_url": "https://cdn.faire.com/fastly/719d1027e640628bd4155f517b5b15104d6284b7ae6bedb878f9cb5ccea74406.png",
    "product_url": "https://www.faire.com",
    "brand": "Moroccan Bags",
    "primary_color": "beige",
    "primary_color_hex": "#e8d8c8"
  },
  {
    "title": "Artisan Gold Toe-Loop Leather Sandals",
    "price": "$45",
    "image_url": "https://cdn.faire.com/fastly/5de53da83491bc2fb0759b2dd0444ee78361a0ba042be646b47c43f525ac065c.jpeg",
    "product_url": "https://www.faire.com",
    "brand": "Moroccan Bags",
    "primary_color": "beige",
    "primary_color_hex": "#e8d8c8"
  },
  {
    "title": "Artisan Handstitched Full-Grain Brown Leather Thong Sandals",
    "price": "$45",
    "image_url": "https://cdn.faire.com/fastly/150e0d887588bf894c36638a96cde2aeaa791c04827cefb1a546229eb7e55172.png",
    "product_url": "https://www.faire.com",
    "brand": "Moroccan Bags",
    "primary_color": "beige",
    "primary_color_hex": "#e8d8c8"
  },
  {
    "title": "Artisan Handwoven Basket with Embroidery",
    "price": "$45",
    "image_url": "https://cdn.faire.com/fastly/e312ca2aa6952e312bf68442f4abe5c17993af93516323014c42598d1fb51183.png",
    "product_url": "https://www.faire.com",
    "brand": "Moroccan Bags",
    "primary_color": "beige",
    "primary_color_hex": "#e8d8c8"
  },
  {
    "title": "Artisan Handwoven Straw Tote with Leather Straps",
    "price": "$45",
    "image_url": "https://cdn.faire.com/fastly/4c72da7cab1dae7d8b7c978872a2136e31077dd6fca50e640d2fbfb32fc48b3f.png",
    "product_url": "https://www.faire.com",
    "brand": "Moroccan Bags",
    "primary_color": "beige",
    "primary_color_hex": "#e8d8c8"
  },
  {
    "title": "Artisan Leather Travelers Journal - Custom Brass Hardware",
    "price": "$45",
    "image_url": "https://cdn.faire.com/fastly/62083d48d44913cabd44113f64f3dd86d2c8821f8fbd587bf975697e23669686.jpeg",
    "product_url": "https://www.faire.com",
    "brand": "Moroccan Bags",
    "primary_color": "beige",
    "primary_color_hex": "#e8d8c8"
  },
  {
    "title": "Artisan Palm Tote with Green Diamond Embroidery",
    "price": "$45",
    "image_url": "https://cdn.faire.com/fastly/19c695b80069271f14e26cb81dc3c80bcabdb914e62052bd75879354ab3aa421.png",
    "product_url": "https://www.faire.com",
    "brand": "Moroccan Bags",
    "primary_color": "beige",
    "primary_color_hex": "#e8d8c8"
  },
  {
    "title": "Artisan Raffia Coil Tissue Box Cover - Marrakesh",
    "price": "$45",
    "image_url": "https://cdn.faire.com/fastly/7efec86ab55370ebb1ab452a43c8734c5f7588211869da2c58f6395931d6583d.png",
    "product_url": "https://www.faire.com",
    "brand": "Moroccan Bags",
    "primary_color": "beige",
    "primary_color_hex": "#e8d8c8"
  },
  {
    "title": "Artisan Woven Raffia & white Leather Tote Bag with Tassel",
    "price": "$45",
    "image_url": "https://cdn.faire.com/fastly/a8175b42d6b815ccccdb4f38e268afb03aea8e0cdfb003e366eb15c707d70168.png",
    "product_url": "https://www.faire.com",
    "brand": "Moroccan Bags",
    "primary_color": "yellow",
    "primary_color_hex": "#ffd700"
  },
  {
    "title": "Artisan Woven Straw Bag with Red Pom Heart & Leather",
    "price": "$45",
    "image_url": "https://cdn.faire.com/fastly/8e7989f73334fc3621abede8913ee7809fb152d2009ee32edbcd01ca2323b920.png",
    "product_url": "https://www.faire.com",
    "brand": "Moroccan Bags",
    "primary_color": "beige",
    "primary_color_hex": "#e8d8c8"
  },
  {
    "title": "Artisan Woven Straw Bag with Yarn Flower and Watermelon",
    "price": "$45",
    "image_url": "https://cdn.faire.com/fastly/1d4140964e23793bd572cf36082706cb5c31acb3b81ecb2c900525b38e5e904b.png",
    "product_url": "https://www.faire.com",
    "brand": "Moroccan Bags",
    "primary_color": "beige",
    "primary_color_hex": "#e8d8c8"
  },
  {
    "title": "Artisan Woven Straw Tote Bag with Gold Winking Eye",
    "price": "$45",
    "image_url": "https://cdn.faire.com/fastly/3f988448056bd2577876ec04670fe7dee015f474d917d87e659c8bd41a63a49d.png",
    "product_url": "https://www.faire.com",
    "brand": "Moroccan Bags",
    "primary_color": "beige",
    "primary_color_hex": "#e8d8c8"
  },
  {
    "title": "Artisan Woven Straw Tote | Hand-Embroidered Floral Basket",
    "price": "$45",
    "image_url": "https://cdn.faire.com/fastly/eba7f52a31dd374044f83f8b8eb1be8415b06d5ab77f3bfb0033247574417676.png",
    "product_url": "https://www.faire.com",
    "brand": "Moroccan Bags",
    "primary_color": "beige",
    "primary_color_hex": "#e8d8c8"
  },
  {
    "title": "Artisanal Charm: Straw Bag with Leather Handles",
    "price": "$45",
    "image_url": "https://cdn.faire.com/fastly/0e8de70b14cd034cab9f1bafa904c7445d47a58a8e62e47e5e69cd63eff7f767.jpeg",
    "product_url": "https://www.faire.com",
    "brand": "Moroccan Bags",
    "primary_color": "beige",
    "primary_color_hex": "#e8d8c8"
  },
  {
    "title": "Authentic Moroccan Straw Bag with  Leather handles",
    "price": "$45",
    "image_url": "https://cdn.faire.com/fastly/9f49737f8e2ee512478de1e9cbcfecc3231c18af36d1f20bc2b4a1fe603d037c.jpeg",
    "product_url": "https://www.faire.com",
    "brand": "Moroccan Bags",
    "primary_color": "beige",
    "primary_color_hex": "#e8d8c8"
  },
  {
    "title": "Basket Backpack with a leather, french market bag",
    "price": "$45",
    "image_url": "https://cdn.faire.com/fastly/b2621726b86b6b7c69564cf6d3b547dcb512c76d9dd316389d16318bfed71e3d.jpeg",
    "product_url": "https://www.faire.com",
    "brand": "Moroccan Bags",
    "primary_color": "brown",
    "primary_color_hex": "#8b5a2b"
  },
  {
    "title": "Basket Backpack with a leather, french market bag.",
    "price": "$45",
    "image_url": "https://cdn.faire.com/fastly/9610d252a4912f2f3a52bc10eee22a1b07d4e8346287fe75e6687af2cc2fdfb5.jpeg",
    "product_url": "https://www.faire.com",
    "brand": "Moroccan Bags",
    "primary_color": "brown",
    "primary_color_hex": "#8b5a2b"
  },
  {
    "title": "Beach Ready Straw Basket Bag",
    "price": "$45",
    "image_url": "https://cdn.faire.com/fastly/db1c6bf869a930dc53022d1474b3fd9fd16d502c7413c95e8945ce0fad5dd117.webp",
    "product_url": "https://www.faire.com",
    "brand": "Moroccan Bags",
    "primary_color": "beige",
    "primary_color_hex": "#e8d8c8"
  },
  {
    "title": "Beautiful LARGE MOROCCAN Reed Basket-Large Woven Beach Bag",
    "price": "$45",
    "image_url": "https://cdn.faire.com/fastly/8df2815f85f33051e73dc84273154b75a66e90948f1569fe3a6a47307059b843.jpeg",
    "product_url": "https://www.faire.com",
    "brand": "Moroccan Bags",
    "primary_color": "beige",
    "primary_color_hex": "#e8d8c8"
  },
  {
    "title": "Beautiful LARGE MOROCCAN Reed Baskets",
    "price": "$45",
    "image_url": "https://cdn.faire.com/fastly/37714e1f98890e54fd167d6daf33a46c5871e91d3122a26f0fdac8f466f23687.webp",
    "product_url": "https://www.faire.com",
    "brand": "Moroccan Bags",
    "primary_color": "beige",
    "primary_color_hex": "#e8d8c8"
  },
  {
    "title": "Beautiful LARGE MOROCCAN Reed Baskets .",
    "price": "$45",
    "image_url": "https://cdn.faire.com/fastly/e30188e929343c9c3442be60b7fffa2ac2efc24b00eb235acb3a59673c80872f.jpeg",
    "product_url": "https://www.faire.com",
    "brand": "Moroccan Bags",
    "primary_color": "beige",
    "primary_color_hex": "#e8d8c8"
  },
  {
    "title": "Beautiful LARGE MOROCCAN Reed Baskets.",
    "price": "$45",
    "image_url": "https://cdn.faire.com/fastly/11ed4649568d8a37ee91647a82b9f7756537a8e5dc6f90ddd384d450d92c002d.jpeg",
    "product_url": "https://www.faire.com",
    "brand": "Moroccan Bags",
    "primary_color": "beige",
    "primary_color_hex": "#e8d8c8"
  },
  {
    "title": "Big Straw Tote Bag - Double leather handles",
    "price": "$45",
    "image_url": "https://cdn.faire.com/fastly/5140eded733d5665aa79b687cf7d61beed196eac1fdde8c75033e164421c1135.webp",
    "product_url": "https://www.faire.com",
    "brand": "Moroccan Bags",
    "primary_color": "beige",
    "primary_color_hex": "#e8d8c8"
  },
  {
    "title": "BLACK Straw and Leather Tote Basket",
    "price": "$45",
    "image_url": "https://cdn.faire.com/fastly/df167e9ebbd6aa0b68522d995ad7bef9cdfc18e6d1b67eac18d2b16a5850ad40.jpeg",
    "product_url": "https://www.faire.com",
    "brand": "Moroccan Bags",
    "primary_color": "beige",
    "primary_color_hex": "#e8d8c8"
  },
  {
    "title": "Brown Leather Tote Bag – Handmade Women’s Studded Shoulder H",
    "price": "$56",
    "image_url": "https://cdn.faire.com/fastly/48e29c1bcf593a88922290c784b89b337dcd091dc02b9a17ba848a6d39e31545.jpeg",
    "product_url": "https://www.faire.com",
    "brand": "Moroccan Bags",
    "primary_color": "beige",
    "primary_color_hex": "#e8d8c8"
  },
  {
    "title": "Camel Brown Boho Crossbody Bag – Moroccan Ethnic Studded Pur",
    "price": "$131",
    "image_url": "https://cdn.faire.com/fastly/d159d3b00181f2a0d1631d3def12ef081e0b8220fe52235696c06e52740cbee2.jpeg",
    "product_url": "https://www.faire.com",
    "brand": "Moroccan Bags",
    "primary_color": "orange",
    "primary_color_hex": "#ffa500"
  },
  {
    "title": "Cherry Blossom Delight: Handwoven Straw Bag",
    "price": "$45",
    "image_url": "https://cdn.faire.com/fastly/8cc463c87843d3445338571749e0fffb9e6516dfec21107d1d3b770bd22fd24d.jpeg",
    "product_url": "https://www.faire.com",
    "brand": "Moroccan Bags",
    "primary_color": "beige",
    "primary_color_hex": "#e8d8c8"
  },
  {
    "title": "Chic French Straw Tote Bag with Leather Handles - Market",
    "price": "$45",
    "image_url": "https://cdn.faire.com/fastly/6b305a5845e67719f3c42c4e39f7e97bb4973f8142047e19caf30f080e07ab9a.jpeg",
    "product_url": "https://www.faire.com",
    "brand": "Moroccan Bags",
    "primary_color": "dark_gray",
    "primary_color_hex": "#111111"
  },
  {
    "title": "Chic Straw Tote: Handcrafted with Premium Leather Handles",
    "price": "$45",
    "image_url": "https://cdn.faire.com/fastly/d2ff69bd4f1e96bb72d329c05de0523019ad55ccd94f9b14660f3d341ad81493.jpeg",
    "product_url": "https://www.faire.com",
    "brand": "Moroccan Bags",
    "primary_color": "beige",
    "primary_color_hex": "#e8d8c8"
  },
  {
    "title": "Classic Elegance: Straw Bag with Leather Handles",
    "price": "$45",
    "image_url": "https://cdn.faire.com/fastly/5713a179c64789761cef4a5a118c5796b56c49ce5af5d96e1fe90173174fab82.jpeg",
    "product_url": "https://www.faire.com",
    "brand": "Moroccan Bags",
    "primary_color": "beige",
    "primary_color_hex": "#e8d8c8"
  },
  {
    "title": "Classic Straw Handbag: Leather Top Handles & Closure",
    "price": "$45",
    "image_url": "https://cdn.faire.com/fastly/41bfe61d3120392a34264819862f4e24687b8d8bb48d235fcaa1ee0a7c44ae95.jpeg",
    "product_url": "https://www.faire.com",
    "brand": "Moroccan Bags",
    "primary_color": "beige",
    "primary_color_hex": "#e8d8c8"
  },
  {
    "title": "Custom Personalized Straw Tote Bag | Embroidered Beach Baske",
    "price": "$45",
    "image_url": "https://cdn.faire.com/fastly/bae07e3dafc6b1dc16bb32508e246e08bb29c53c40c53156e49e2bb23ef3f608.png",
    "product_url": "https://www.faire.com",
    "brand": "Moroccan Bags",
    "primary_color": "beige",
    "primary_color_hex": "#e8d8c8"
  },
  {
    "title": "Dark Brown Boho Bag – Moroccan Studded Crossbody Purse – Eth",
    "price": "$97",
    "image_url": "https://cdn.faire.com/fastly/37076fe56823c7f0cf137cb5e7daded845c7df160e14c308630ad0af086309e1.jpeg",
    "product_url": "https://www.faire.com",
    "brand": "Moroccan Bags",
    "primary_color": "brown",
    "primary_color_hex": "#8b5a2b"
  },
  {
    "title": "Embroidered Tote Bag - Moroccan-Inspired Suede Handbag.",
    "price": "$45",
    "image_url": "https://cdn.faire.com/fastly/6f5c3ba281e4b57c8d168f5b290445e66706e82eaddf2dc1f660cf6541e21a75.jpeg",
    "product_url": "https://www.faire.com",
    "brand": "Moroccan Bags",
    "primary_color": "dark_gray",
    "primary_color_hex": "#111111"
  },
  {
    "title": "Evil Eye Straw beach bag, bridesmaid beach bag",
    "price": "$45",
    "image_url": "https://cdn.faire.com/fastly/8a8406423127f5c3dad2c2084ee30c05543e223a7e08444452d1a690a8a8c4f0.jpeg",
    "product_url": "https://www.faire.com",
    "brand": "Moroccan Bags",
    "primary_color": "beige",
    "primary_color_hex": "#e8d8c8"
  },
  {
    "title": "Flamingo Straw Bag with Leather Handles",
    "price": "$45",
    "image_url": "https://cdn.faire.com/fastly/3ed4d86517f11949bd8e88c2e74218fb32bc9ee8a22ec677c3dcb1d0762c6b9b.jpeg",
    "product_url": "https://www.faire.com",
    "brand": "Moroccan Bags",
    "primary_color": "beige",
    "primary_color_hex": "#e8d8c8"
  },
  {
    "title": "Artisan Handwoven Straw Basket with Floral Embroidery",
    "price": "$45",
    "image_url": "https://cdn.faire.com/fastly/1a03ebd7b2b04aabedf1af18f7aa48e714621471204c173706de3f86cc255370.png",
    "product_url": "https://www.faire.com",
    "brand": "Moroccan Home",
    "primary_color": "beige",
    "primary_color_hex": "#e8d8c8"
  },
  {
    "title": "Basket Large palm leaf / Wicker",
    "price": "$45",
    "image_url": "https://cdn.faire.com/fastly/efff7d5bbcc63681f1e52dc4273025342cf01413d92c1cd19057fe7b8c277da1.jpeg",
    "product_url": "https://www.faire.com",
    "brand": "Moroccan Home",
    "primary_color": "beige",
    "primary_color_hex": "#e8d8c8"
  },
  {
    "title": "Bat Halloween Trick or Treat Basket- Woven Candy Tote Bag",
    "price": "$45",
    "image_url": "https://cdn.faire.com/fastly/b70cbbc94bf9ee7de4d2f2910ad3977a99018719d480bccb550b7814a391db51.webp",
    "product_url": "https://www.faire.com",
    "brand": "Moroccan Home",
    "primary_color": "beige",
    "primary_color_hex": "#e8d8c8"
  },
  {
    "title": "Boho-Luxury Black Berber cushion cover – Handira style from",
    "price": "$45",
    "image_url": "https://cdn.faire.com/fastly/ab1628520b2add4d90df8d5e5230e8280e7ab6dc9755a5ced8120de6e76047a2.png",
    "product_url": "https://www.faire.com",
    "brand": "Moroccan Home",
    "primary_color": "beige",
    "primary_color_hex": "#e8d8c8"
  },
  {
    "title": "FRENCH MARKET BASKET - DOUBLE STRAPS ( Leather )",
    "price": "$45",
    "image_url": "https://cdn.faire.com/fastly/9cb67e66c8c5cc59dd7dc007fff20345c3fea3ec3e5c62f4cda9f3cf64e75c1d.webp",
    "product_url": "https://www.faire.com",
    "brand": "Moroccan Home",
    "primary_color": "beige",
    "primary_color_hex": "#e8d8c8"
  },
  {
    "title": "French Market Basket with Leather Handles",
    "price": "$45",
    "image_url": "https://cdn.faire.com/fastly/8f0b75f5a47bfc3d18962b494e0c834ba9a88c1f16190f0a9bb0cf6b927cec0c.jpeg",
    "product_url": "https://www.faire.com",
    "brand": "Moroccan Home",
    "primary_color": "beige",
    "primary_color_hex": "#e8d8c8"
  },
  {
    "title": "French Market Basket with Short & Long Leather Handles",
    "price": "$45",
    "image_url": "https://cdn.faire.com/fastly/d7bb609070d2a04e556725822bf13d7f6c9bf0caa136207fcd474c587a42862b.png",
    "product_url": "https://www.faire.com",
    "brand": "Moroccan Home",
    "primary_color": "beige",
    "primary_color_hex": "#e8d8c8"
  },
  {
    "title": "Fringed Wall Mounted Straw Hat - Customizable",
    "price": "$45",
    "image_url": "https://cdn.faire.com/fastly/d1ccaae8bb052ee00dfada1e3c887b723c03df4c6566cfbd1f9014610ab0dcfd.jpeg",
    "product_url": "https://www.faire.com",
    "brand": "Moroccan Home",
    "primary_color": "beige",
    "primary_color_hex": "#e8d8c8"
  },
  {
    "title": "Fruit basket with lace edge",
    "price": "$45",
    "image_url": "https://cdn.faire.com/fastly/a3b5b817dcbc60dc36d0dd13762f39b1350ffb6bc7995b2c9ac101fe6aa32507.jpeg",
    "product_url": "https://www.faire.com",
    "brand": "Moroccan Home",
    "primary_color": "beige",
    "primary_color_hex": "#e8d8c8"
  },
  {
    "title": "Ghost Trick or Treat Basket: Woven Halloween Candy Tote",
    "price": "$45",
    "image_url": "https://cdn.faire.com/fastly/0de30d4ca7978080de73fdb26a507eb537ba44a4c6081c74bb181d8bca34ae55.jpeg",
    "product_url": "https://www.faire.com",
    "brand": "Moroccan Home",
    "primary_color": "beige",
    "primary_color_hex": "#e8d8c8"
  },
  {
    "title": "Golden Faux Leather Moroccan Pouf – Decorative Cushion",
    "price": "$45",
    "image_url": "https://cdn.faire.com/fastly/a097607b36c4f7ad626b9a2eef4338ed27fb5dfe6f0de73a542b3851e34146eb.png",
    "product_url": "https://www.faire.com",
    "brand": "Moroccan Home",
    "primary_color": "beige",
    "primary_color_hex": "#e8d8c8"
  },
  {
    "title": "Hand-woven palm leaf storage with leather trim",
    "price": "$45",
    "image_url": "https://cdn.faire.com/fastly/bf3d01742f58e7960c249a5d88a820d1e9c328edc9f70f1f8cfb584ad5135e98.webp",
    "product_url": "https://www.faire.com",
    "brand": "Moroccan Home",
    "primary_color": "beige",
    "primary_color_hex": "#e8d8c8"
  },
  {
    "title": "Handcrafted Moroccan Leather Bar Stool with Backrest",
    "price": "$45",
    "image_url": "https://cdn.faire.com/fastly/9a9c72d8d6ecde19311a927f0f338555e1ef97a554073f2653c7a1aea31417f7.jpeg",
    "product_url": "https://www.faire.com",
    "brand": "Moroccan Home",
    "primary_color": "beige",
    "primary_color_hex": "#e8d8c8"
  },
  {
    "title": "Handcrafted Moroccan Palm Leaf Tote with Leather Handles",
    "price": "$45",
    "image_url": "https://cdn.faire.com/fastly/fcaa02de7318b778fa1d33afafc2e09fbfe5a7a16e6bc9ee3cfd9619a5ce92de.png",
    "product_url": "https://www.faire.com",
    "brand": "Moroccan Home",
    "primary_color": "beige",
    "primary_color_hex": "#e8d8c8"
  },
  {
    "title": "Handcrafted Rustic Picnic Basket – Eco-Friendly",
    "price": "$45",
    "image_url": "https://cdn.faire.com/fastly/271c09831ce2092e25d95d25ae7e146078ae4ae0e48c09c8e5dc3dc7ad4197e9.webp",
    "product_url": "https://www.faire.com",
    "brand": "Moroccan Home",
    "primary_color": "beige",
    "primary_color_hex": "#e8d8c8"
  },
  {
    "title": "Handcrafted Straw Basket with Embroidered Floral Design",
    "price": "$45",
    "image_url": "https://cdn.faire.com/fastly/ec24209c141ab632293e3c1b2e80f36601d54c2b701f2b8615a15c71e66b2f2d.png",
    "product_url": "https://www.faire.com",
    "brand": "Moroccan Home",
    "primary_color": "beige",
    "primary_color_hex": "#e8d8c8"
  },
  {
    "title": "Handcrafted Straw Basket with Hearts Design",
    "price": "$45",
    "image_url": "https://cdn.faire.com/fastly/6bba83319898384a9d306f25e58bb516ae95678f7eec43f5b58c6871f8dfe95a.jpeg",
    "product_url": "https://www.faire.com",
    "brand": "Moroccan Home",
    "primary_color": "beige",
    "primary_color_hex": "#e8d8c8"
  },
  {
    "title": "Handcrafted Straw Tote Featuring Leather Handles and Sequins",
    "price": "$45",
    "image_url": "https://cdn.faire.com/fastly/88e109a693029eb07d3f5630f3301106ad1f9560752e572ba4d8e880080f688c.png",
    "product_url": "https://www.faire.com",
    "brand": "Moroccan Home",
    "primary_color": "beige",
    "primary_color_hex": "#e8d8c8"
  },
  {
    "title": "Handmade Embroidered Straw Basket",
    "price": "$45",
    "image_url": "https://cdn.faire.com/fastly/7f76863bcfb08a4887b9e8dd7208f4584936276780e98dbea9805a56f7c45fd4.jpeg",
    "product_url": "https://www.faire.com",
    "brand": "Moroccan Home",
    "primary_color": "beige",
    "primary_color_hex": "#e8d8c8"
  },
  {
    "title": "Handmade Embroidered Straw Basket with Leather Handles",
    "price": "$45",
    "image_url": "https://cdn.faire.com/fastly/4b1b8e2198b3e83bcf8492b07c4f0227e2340c2aedda3bead4d2f461cd4149d7.png",
    "product_url": "https://www.faire.com",
    "brand": "Moroccan Home",
    "primary_color": "beige",
    "primary_color_hex": "#e8d8c8"
  },
  {
    "title": "Handmade Embroidered Straw Basket – Floral Design",
    "price": "$45",
    "image_url": "https://cdn.faire.com/fastly/e66f33037864bd653195c9184cd07e2bfbd17966619be90ca4d480f6d1812ebf.png",
    "product_url": "https://www.faire.com",
    "brand": "Moroccan Home",
    "primary_color": "beige",
    "primary_color_hex": "#e8d8c8"
  },
  {
    "title": "Handmade Mini Reed Basket with Cherry Pom-Poms",
    "price": "$45",
    "image_url": "https://cdn.faire.com/fastly/0e27ed9ff4c4ddd8c91f9a806af0f177bb94a533f740f932c73c5bf9aa84e38d.png",
    "product_url": "https://www.faire.com",
    "brand": "Moroccan Home",
    "primary_color": "beige",
    "primary_color_hex": "#e8d8c8"
  },
  {
    "title": "Handmade Mini Reed Basket with Lemon Design",
    "price": "$45",
    "image_url": "https://cdn.faire.com/fastly/d721bd364798b819710044e4d18a396b49064b08848b911daed1c0cf21381fdc.png",
    "product_url": "https://www.faire.com",
    "brand": "Moroccan Home",
    "primary_color": "beige",
    "primary_color_hex": "#e8d8c8"
  },
  {
    "title": "Handmade Mini Reed Basket with Strawberry Design",
    "price": "$45",
    "image_url": "https://cdn.faire.com/fastly/f2619cd4c042eb0613bdfe162d66889d971f48291d6918a146a9007bcbe2bf08.png",
    "product_url": "https://www.faire.com",
    "brand": "Moroccan Home",
    "primary_color": "beige",
    "primary_color_hex": "#e8d8c8"
  },
  {
    "title": "Handmade Moroccan Doum Fiber Pendant Light .",
    "price": "$45",
    "image_url": "https://cdn.faire.com/fastly/bb07bea2644e195aaa238f554187b129e546df74c6c5367f3ee5804288ff411c.jpeg",
    "product_url": "https://www.faire.com",
    "brand": "Moroccan Home",
    "primary_color": "beige",
    "primary_color_hex": "#e8d8c8"
  },
  {
    "title": "Handmade Moroccan Leather Pouf - Embroidered Ottoman Decor",
    "price": "$45",
    "image_url": "https://cdn.faire.com/fastly/89ed6063a123fb68654415c582f8b6b6cebced0bcde1cc3da8e9aa588ecace44.png",
    "product_url": "https://www.faire.com",
    "brand": "Moroccan Home",
    "primary_color": "beige",
    "primary_color_hex": "#808080"
  },
  {
    "title": "Handmade Moroccan Leather Pouf - Embroidered Ottoman Design",
    "price": "$45",
    "image_url": "https://cdn.faire.com/fastly/5cfc6f71b28ff8431791a86f7dc802c14b37d4b41ed926b4ac77a4bfd5e237df.png",
    "product_url": "https://www.faire.com",
    "brand": "Moroccan Home",
    "primary_color": "beige",
    "primary_color_hex": "#e8d8c8"
  },
  {
    "title": "Handmade Moroccan Leather Pouf - Tan Ottoman with Embroidery",
    "price": "$45",
    "image_url": "https://cdn.faire.com/fastly/ffe32332579cca30a722d41b81bed32e0775929b73e0f7b3f778b7289c0780b8.png",
    "product_url": "https://www.faire.com",
    "brand": "Moroccan Home",
    "primary_color": "beige",
    "primary_color_hex": "#e8d8c8"
  },
  {
    "title": "Handmade Moroccan Mini Sequin Straw Basket",
    "price": "$45",
    "image_url": "https://cdn.faire.com/fastly/09f7e6fe1352b1d75885cdcf11222a14ed4ed37a3f7bf17a6a117516d6550d07.webp",
    "product_url": "https://www.faire.com",
    "brand": "Moroccan Home",
    "primary_color": "beige",
    "primary_color_hex": "#e8d8c8"
  },
  {
    "title": "Handmade Moroccan Wood Armchair with Woven Leather Seat",
    "price": "$45",
    "image_url": "https://cdn.faire.com/fastly/e239b9fea1e8718208f4d8a50402d955c14bc659da93c58d105b5138359c436c.jpeg",
    "product_url": "https://www.faire.com",
    "brand": "Moroccan Home",
    "primary_color": "beige",
    "primary_color_hex": "#e8d8c8"
  },
  {
    "title": "Handmade Reed Basket – Sustainable Home Storage Organizer",
    "price": "$45",
    "image_url": "https://cdn.faire.com/fastly/5c0d30e215b47c0ca66b33396d4d19d22942190f1fc0c33e5331b23b09dde35f.png",
    "product_url": "https://www.faire.com",
    "brand": "Moroccan Home",
    "primary_color": "beige",
    "primary_color_hex": "#e8d8c8"
  },
  {
    "title": "Handmade Reed Storage Basket with Leather Handles",
    "price": "$45",
    "image_url": "https://cdn.faire.com/fastly/1605c57e7abf321114501116727e568e6b6d11b438a3312952405ade49eaaf59.png",
    "product_url": "https://www.faire.com",
    "brand": "Moroccan Home",
    "primary_color": "beige",
    "primary_color_hex": "#e8d8c8"
  },
  {
    "title": "Handmade Reed Storage Baskets for Home Organization",
    "price": "$45",
    "image_url": "https://cdn.faire.com/fastly/7516b197c871e797322d87ad5fe506e3e33883ce005b79b491b2bd41655ba72a.jpeg",
    "product_url": "https://www.faire.com",
    "brand": "Moroccan Home",
    "primary_color": "beige",
    "primary_color_hex": "#e8d8c8"
  },
  {
    "title": "Handmade Straw Basket with Sequin Design & Leather Handles",
    "price": "$45",
    "image_url": "https://cdn.faire.com/fastly/51b7686b28e2cedddfdf9752433d7b77f316967dff990aee5d703dfc06dff8fb.png",
    "product_url": "https://www.faire.com",
    "brand": "Moroccan Home",
    "primary_color": "beige",
    "primary_color_hex": "#e8d8c8"
  },
  {
    "title": "Handmade Tall Straw Tote Bag with Leather Handles",
    "price": "$45",
    "image_url": "https://cdn.faire.com/fastly/b1b95f6473435b9b479a997620dcd9064eaa4c59ca6228070d3459c4ca7ca54d.png",
    "product_url": "https://www.faire.com",
    "brand": "Moroccan Home",
    "primary_color": "beige",
    "primary_color_hex": "#e8d8c8"
  },
  {
    "title": "Handmade Woven Reed Basket with Thin Leather Handles",
    "price": "$45",
    "image_url": "https://cdn.faire.com/fastly/629b3b06e0ec5169c24c10157138ce244917f6bae72b519492b85560374b7a24.jpeg",
    "product_url": "https://www.faire.com",
    "brand": "Moroccan Home",
    "primary_color": "beige",
    "primary_color_hex": "#e8d8c8"
  },
  {
    "title": "Handwoven Floral Embroidered Straw Basket – Artisan Design",
    "price": "$45",
    "image_url": "https://cdn.faire.com/fastly/980ebec71edb411f7a41332d402ccd0a519c3180fdce441abdbf76c1239b00c8.png",
    "product_url": "https://www.faire.com",
    "brand": "Moroccan Home",
    "primary_color": "beige",
    "primary_color_hex": "#e8d8c8"
  },
  {
    "title": "Handwoven Moroccan basket – Durable reeds and leather handle",
    "price": "$45",
    "image_url": "https://cdn.faire.com/fastly/076359665affe89bf2638600db4c1edab9360df8b9ed380ddde24abb93286f5c.webp",
    "product_url": "https://www.faire.com",
    "brand": "Moroccan Home",
    "primary_color": "beige",
    "primary_color_hex": "#e8d8c8"
  },
  {
    "title": "Handwoven Moroccan Straw Basket with Leather Handles.",
    "price": "$45",
    "image_url": "https://cdn.faire.com/fastly/cd9ca48780cc97e715c8fb64c1febfaea2859ed329b4b085fb583e680fcd20dd.png",
    "product_url": "https://www.faire.com",
    "brand": "Moroccan Home",
    "primary_color": "beige",
    "primary_color_hex": "#e8d8c8"
  },
  {
    "title": "Handwoven Moroccan Straw Basket with Strawberry Embroidery",
    "price": "$45",
    "image_url": "https://cdn.faire.com/fastly/5946c64cd2c1d123da0ce2196549943940d47de373ddb153eee69849615c0892.jpeg",
    "product_url": "https://www.faire.com",
    "brand": "Moroccan Home",
    "primary_color": "beige",
    "primary_color_hex": "#e8d8c8"
  }
]